{
  "AutoReset": true,
  "Melee": [
    34,
    20,
    30,
    22,
    39,
    32,
    37,
    21,
    19
  ],
  "Ranged": [
    27,
    35,
    25,
    31,
    38,
    23,
    40,
    24,
    28,
    33
  ],
  "HeliosPP": 0.7,
  "ABPP": 0.7,
  "BeneficPP": 0.7,
  "AHPP": 0.7,
  "MedicalII": false,
  "CureIII": false,
  "AfflatusSolace": false,
  "Aquaveil": true,
  "Assize": true,
  "DivineBenison": true,
  "Plenary": true,
  "Tetragrammaton": true,
  "PresenceofMind": true,
  "ThinAir": true,
  "AfflatusRapturePP": 0.8,
  "CureIIIPP": 0.3,
  "MedicalIIPP": 0.7,
  "AquaveilPP": 0.9,
  "DivineBenisonPP": 0.8,
  "PlenaryPP": 0.6,
  "TetragrammatonPP": 0.75,
  "AfflatusSolacePP": 0.4,
  "Curenum": 4,
  "time": 1500,
  "opener": 0,
  "StyleSetting": {},
  "CelestialIntersectionPercentage": 0.8,
  "CelestialOppositionPercentage": 0.8,
  "CollectiveUnconsciousPercentage": 0.8,
  "EssentialDignityPercentage": 0.3,
  "ExaltationPercentage": 0.9,
  "HoroscopePercentage": 0.9,
  "CrownCardPercentage": 0.8,
  "SynastryPercentage": 0.8,
  "AspectedBeneficPercentage": 0.7,
  "AspectedHeliosPercentage": 0.7,
  "BeneficIIPercentage": 0.6,
  "HeliosPercentage": 0.75,
  "Openerearthstar": false,
  "Openerearthstartime": 5000,
  "OpenerNeutralSect": false,
  "OpenerNeutralSecttime": 20000,
  "OpenerHoroscope": false,
  "OpenerHoroscopetime": 15000,
  "Esuna": 2,
  "stack": 3,
  "OnlyTank": false,
  "JobViewSave": {
    "MainColor": {
      "X": 0.15686275,
      "Y": 0.6784314,
      "Z": 0.27450982,
      "W": 0.8
    },
    "QtWindowBgAlpha": 0.3,
    "QtButtonSize": {
      "X": 95.0,
      "Y": 40.0
    },
    "QtHotkeySize": {
      "X": 56.0,
      "Y": 56.0
    },
    "QtUnVisibleList": [],
    "QtLineCount": 3,
    "HotkeyConfig": {},
    "QtHotkeyConfig": {},
    "HotkeyUnVisibleList": [],
    "HotkeyLineCount": 4,
    "AutoReset": true,
    "ShowQT": true,
    "ShowHotkey": true
  }
}